TDA/BuZZ.py
TDA/TGZZ.py
sporktda/__init__.py
sporktda/TDA/BuZZ.py
sporktda/TDA/TGZZ.py
sporktda/TDA/__init__.py
sporktda-0.0.6.dist-info/METADATA
sporktda-0.0.6.dist-info/WHEEL
sporktda-0.0.6.dist-info/top_level.txt
sporktda-0.0.6.dist-info/RECORD
