Metadata-Version: 2.1
Name: sporktda
Version: 0.0.6
Summary: Spork - the teaspoon companion
Author-email: Elizabeth Munch <muncheli@msu.edu>
Project-URL: repository, https://github.com/TeaspoonTDA/sporktda
Project-URL: homepage, https://github.com/TeaspoonTDA/sporktda
Project-URL: documentation, https://teaspoontda.github.io/sporktda/
Classifier: Programming Language :: Python :: 3
Classifier: Operating System :: OS Independent
Requires-Python: >=3.6
Requires-Dist: dionysus
Requires-Dist: pandas
Requires-Dist: matplotlib
Requires-Dist: ripser
Requires-Dist: teaspoon >=1.4.0
Requires-Dist: gudhi
Requires-Dist: networkx
Requires-Dist: numpy
